{"session":"ums-memory","generated_at":"2026-03-01T00:58:30.202372+07:00","format":"handoff","files":[{"path":"CLAUDE.md","action":"created","context":"│        Welcome back Petr!        │ Run /init to create a CLAUDE.md file with instructions for Claude │"},{"path":".github/hooks/dcg.json","action":"created"},{"path":".gitignore","action":"created"},{"path":".ntm/logs/am-ums-memory.log","action":"created"},{"path":".ntm/logs/bd-ums-memory.log","action":"created"},{"path":".ntm/logs/cm-ums-memory.log","action":"created"},{"path":".ntm/pids/bd-ums-memory.pid","action":"created"},{"path":".ntm/pids/cm-ums-memory.pid","action":"created"},{"path":".ntm/rate_limits.json","action":"created"},{"path":".ntm/recipes.toml","action":"created"},{"path":".ntm/summaries/ums-memory-20260301-003840.json","action":"created"},{"path":".ntm/summaries/ums-memory-20260301-004918.json","action":"created"},{"path":".ntm/summaries/ums-memory-20260301-005120.json","action":"created"},{"path":"PLAN.md","action":"created"},{"path":"mcp_agent_mail/","action":"created"}],"errors":["❯ Try \"fix lint errors\"","`mcp_agent_mail` failed","failed: handshaking with","MCP server failed: Send","message error Transport","t\u003e\u003e] error: Client","error: error sending"],"token_estimate":256,"text":"version: \"1.0\"\nsession: ums-memory\ndate: \"2026-03-01\"\ncreated_at: 2026-03-01T00:58:30.202375+07:00\nupdated_at: 2026-03-01T00:58:30.202375+07:00\nstatus: blocked\noutcome: PARTIAL_MINUS\ngoal: Session summary\nnow: Review recent changes\ntest: \"\"\nblockers:\n    - ❯ Try \"fix lint errors\"\n    - '`mcp_agent_mail` failed'\n    - 'failed: handshaking with'\n    - 'MCP server failed: Send'\n    - message error Transport\n    - 't\u003e\u003e] error: Client'\n    - 'error: error sending'\nfiles:\n    created:\n        - CLAUDE.md\n        - .github/hooks/dcg.json\n        - .gitignore\n        - .ntm/logs/am-ums-memory.log\n        - .ntm/logs/bd-ums-memory.log\n        - .ntm/logs/cm-ums-memory.log\n        - .ntm/pids/bd-ums-memory.pid\n        - .ntm/pids/cm-ums-memory.pid\n        - .ntm/rate_limits.json\n        - .ntm/recipes.toml\n        - .ntm/summaries/ums-memory-20260301-003840.json\n        - .ntm/summaries/ums-memory-20260301-004918.json\n        - .ntm/summaries/ums-memory-20260301-005120.json\n        - PLAN.md\n        - mcp_agent_mail/","handoff":{"Version":"1.0","Session":"ums-memory","Date":"2026-03-01","CreatedAt":"2026-03-01T00:58:30.202375+07:00","UpdatedAt":"2026-03-01T00:58:30.202375+07:00","Status":"blocked","Outcome":"PARTIAL_MINUS","Goal":"Session summary","Now":"Review recent changes","Test":"","DoneThisSession":null,"Blockers":["❯ Try \"fix lint errors\"","`mcp_agent_mail` failed","failed: handshaking with","MCP server failed: Send","message error Transport","t\u003e\u003e] error: Client","error: error sending"],"Questions":null,"Decisions":null,"Findings":null,"Worked":null,"Failed":null,"Next":null,"Files":{"Created":["CLAUDE.md",".github/hooks/dcg.json",".gitignore",".ntm/logs/am-ums-memory.log",".ntm/logs/bd-ums-memory.log",".ntm/logs/cm-ums-memory.log",".ntm/pids/bd-ums-memory.pid",".ntm/pids/cm-ums-memory.pid",".ntm/rate_limits.json",".ntm/recipes.toml",".ntm/summaries/ums-memory-20260301-003840.json",".ntm/summaries/ums-memory-20260301-004918.json",".ntm/summaries/ums-memory-20260301-005120.json","PLAN.md","mcp_agent_mail/"],"Modified":null,"Deleted":null},"ActiveBeads":null,"AgentMailThreads":null,"CMMemories":null,"AgentID":"","AgentType":"","PaneID":"","TokensUsed":0,"TokensMax":0,"TokensPct":0,"ReservationTransfer":null}}
