{"session":"ums-memory","generated_at":"2026-03-01T00:38:40.568162+07:00","format":"handoff","files":[{"path":"logging.py","action":"created","context":"❯ Try \"create a util logging.py that...\""},{"path":"GEMINI.md","action":"unknown","context":"1 GEMINI.md file"},{"path":".github/hooks/dcg.json","action":"created"},{"path":".gitignore","action":"created"},{"path":".ntm/logs/am-ums-memory.log","action":"created"},{"path":".ntm/logs/bd-ums-memory.log","action":"created"},{"path":".ntm/logs/cm-ums-memory.log","action":"created"},{"path":".ntm/pids/bd-ums-memory.pid","action":"created"},{"path":".ntm/pids/cm-ums-memory.pid","action":"created"},{"path":".ntm/rate_limits.json","action":"created"},{"path":"PLAN.md","action":"created"},{"path":"mcp_agent_mail/","action":"created"}],"errors":["Error: Unknown feature flag: web_search=live","'PurpleDesert' --limit 20] failed for event SessionStart."],"token_estimate":191,"text":"version: \"1.0\"\nsession: ums-memory\ndate: \"2026-03-01\"\ncreated_at: 2026-03-01T00:38:40.568393+07:00\nupdated_at: 2026-03-01T00:38:40.568393+07:00\nstatus: blocked\noutcome: PARTIAL_MINUS\ngoal: Session summary\nnow: Review recent changes\ntest: \"\"\nblockers:\n    - 'Error: Unknown feature flag: web_search=live'\n    - '''PurpleDesert'' --limit 20] failed for event SessionStart.'\nfiles:\n    created:\n        - logging.py\n        - .github/hooks/dcg.json\n        - .gitignore\n        - .ntm/logs/am-ums-memory.log\n        - .ntm/logs/bd-ums-memory.log\n        - .ntm/logs/cm-ums-memory.log\n        - .ntm/pids/bd-ums-memory.pid\n        - .ntm/pids/cm-ums-memory.pid\n        - .ntm/rate_limits.json\n        - PLAN.md\n        - mcp_agent_mail/\n    modified:\n        - GEMINI.md","handoff":{"Version":"1.0","Session":"ums-memory","Date":"2026-03-01","CreatedAt":"2026-03-01T00:38:40.568393+07:00","UpdatedAt":"2026-03-01T00:38:40.568393+07:00","Status":"blocked","Outcome":"PARTIAL_MINUS","Goal":"Session summary","Now":"Review recent changes","Test":"","DoneThisSession":null,"Blockers":["Error: Unknown feature flag: web_search=live","'PurpleDesert' --limit 20] failed for event SessionStart."],"Questions":null,"Decisions":null,"Findings":null,"Worked":null,"Failed":null,"Next":null,"Files":{"Created":["logging.py",".github/hooks/dcg.json",".gitignore",".ntm/logs/am-ums-memory.log",".ntm/logs/bd-ums-memory.log",".ntm/logs/cm-ums-memory.log",".ntm/pids/bd-ums-memory.pid",".ntm/pids/cm-ums-memory.pid",".ntm/rate_limits.json","PLAN.md","mcp_agent_mail/"],"Modified":["GEMINI.md"],"Deleted":null},"ActiveBeads":null,"AgentMailThreads":null,"CMMemories":null,"AgentID":"","AgentType":"","PaneID":"","TokensUsed":0,"TokensMax":0,"TokensPct":0,"ReservationTransfer":null}}
