{"session":"ums-memory","generated_at":"2026-03-01T00:49:18.065478+07:00","format":"handoff","files":[{"path":"GEMINI.md","action":"unknown","context":"1 GEMINI.md file"},{"path":".github/hooks/dcg.json","action":"created"},{"path":".gitignore","action":"created"},{"path":".ntm/logs/am-ums-memory.log","action":"created"},{"path":".ntm/logs/bd-ums-memory.log","action":"created"},{"path":".ntm/logs/cm-ums-memory.log","action":"created"},{"path":".ntm/pids/bd-ums-memory.pid","action":"created"},{"path":".ntm/pids/cm-ums-memory.pid","action":"created"},{"path":".ntm/rate_limits.json","action":"created"},{"path":".ntm/recipes.toml","action":"created"},{"path":".ntm/summaries/ums-memory-20260301-003840.json","action":"created"},{"path":"PLAN.md","action":"created"},{"path":"mcp_agent_mail/","action":"created"}],"errors":["❯ Try \"fix typecheck errors\"","Error: Unknown feature flag: web_search","Error: Unknown feature flag: web_search=","--limit 20] failed for event"],"token_estimate":219,"text":"version: \"1.0\"\nsession: ums-memory\ndate: \"2026-03-01\"\ncreated_at: 2026-03-01T00:49:18.065483+07:00\nupdated_at: 2026-03-01T00:49:18.065483+07:00\nstatus: blocked\noutcome: PARTIAL_MINUS\ngoal: Session summary\nnow: Review recent changes\ntest: \"\"\nblockers:\n    - ❯ Try \"fix typecheck errors\"\n    - 'Error: Unknown feature flag: web_search'\n    - 'Error: Unknown feature flag: web_search='\n    - --limit 20] failed for event\nfiles:\n    created:\n        - .github/hooks/dcg.json\n        - .gitignore\n        - .ntm/logs/am-ums-memory.log\n        - .ntm/logs/bd-ums-memory.log\n        - .ntm/logs/cm-ums-memory.log\n        - .ntm/pids/bd-ums-memory.pid\n        - .ntm/pids/cm-ums-memory.pid\n        - .ntm/rate_limits.json\n        - .ntm/recipes.toml\n        - .ntm/summaries/ums-memory-20260301-003840.json\n        - PLAN.md\n        - mcp_agent_mail/\n    modified:\n        - GEMINI.md","handoff":{"Version":"1.0","Session":"ums-memory","Date":"2026-03-01","CreatedAt":"2026-03-01T00:49:18.065483+07:00","UpdatedAt":"2026-03-01T00:49:18.065483+07:00","Status":"blocked","Outcome":"PARTIAL_MINUS","Goal":"Session summary","Now":"Review recent changes","Test":"","DoneThisSession":null,"Blockers":["❯ Try \"fix typecheck errors\"","Error: Unknown feature flag: web_search","Error: Unknown feature flag: web_search=","--limit 20] failed for event"],"Questions":null,"Decisions":null,"Findings":null,"Worked":null,"Failed":null,"Next":null,"Files":{"Created":[".github/hooks/dcg.json",".gitignore",".ntm/logs/am-ums-memory.log",".ntm/logs/bd-ums-memory.log",".ntm/logs/cm-ums-memory.log",".ntm/pids/bd-ums-memory.pid",".ntm/pids/cm-ums-memory.pid",".ntm/rate_limits.json",".ntm/recipes.toml",".ntm/summaries/ums-memory-20260301-003840.json","PLAN.md","mcp_agent_mail/"],"Modified":["GEMINI.md"],"Deleted":null},"ActiveBeads":null,"AgentMailThreads":null,"CMMemories":null,"AgentID":"","AgentType":"","PaneID":"","TokensUsed":0,"TokensMax":0,"TokensPct":0,"ReservationTransfer":null}}
